setup.cfg
setup.py
discomll/__init__.py
discomll/dataset.py
discomll.egg-info/PKG-INFO
discomll.egg-info/SOURCES.txt
discomll.egg-info/dependency_links.txt
discomll.egg-info/top_level.txt
discomll/classification/__init__.py
discomll/classification/linear_svm.py
discomll/classification/logistic_regression.py
discomll/classification/naivebayes.py
discomll/clustering/__init__.py
discomll/clustering/kmeans.py
discomll/datasets/__init__.py
discomll/datasets/breast_cancer_wisconsin.names.txt
discomll/datasets/breast_cancer_wisconsin_cont.txt
discomll/datasets/breast_cancer_wisconsin_cont_test.txt
discomll/datasets/breast_cancer_wisconsin_disc.txt
discomll/datasets/breast_cancer_wisconsin_disc_test.txt
discomll/datasets/breastcancer_meta.csv
discomll/datasets/chunk_testdata.sh
discomll/datasets/ex3.txt
discomll/datasets/ex3_test.txt
discomll/datasets/ex4.txt
discomll/datasets/iris.names.txt
discomll/datasets/iris.txt
discomll/datasets/iris_meta.csv
discomll/datasets/iris_test.txt
discomll/datasets/regression_data1.txt
discomll/datasets/regression_data2.txt
discomll/datasets/regression_data_test1.txt
discomll/datasets/regression_data_test2.txt
discomll/ensemble/__init__.py
discomll/ensemble/distributed_random_forest.py
discomll/ensemble/distributed_weighted_forest.py
discomll/ensemble/distributed_weighted_forest_rand.py
discomll/ensemble/forest_distributed_decision_trees.py
discomll/ensemble/core/__init__.py
discomll/ensemble/core/decision_tree.py
discomll/ensemble/core/k_medoids.py
discomll/ensemble/core/measures.py
discomll/examples/__init__.py
discomll/examples/chunk_testdata.sh
discomll/examples/big_data/__init__.py
discomll/examples/big_data/drf_lymphography.py
discomll/examples/big_data/drf_segmentation.py
discomll/examples/big_data/dwfr_lymphography.py
discomll/examples/big_data/dwfr_segmentation.py
discomll/examples/big_data/fddt_lymphography.py
discomll/examples/big_data/fddt_segmentation.py
discomll/examples/big_data/kmeans_linear.py
discomll/examples/big_data/kmeans_segmentation.py
discomll/examples/big_data/linreg_fraction.py
discomll/examples/big_data/linreg_linear.py
