Metadata-Version: 1.0
Name: discomll
Version: 0.1.4.2
Summary: Disco Machine Learning Library.
Home-page: https://github.com/romanorac/discomll
Author: Roman Orac
Author-email: orac.roman@gmail.com
License: Apache License, Version 2.0
Platform: UNKNOWN
